mercury_oxide-0.1.0.dist-info/METADATA
mercury_oxide-0.1.0.dist-info/WHEEL
mercury_oxide.cpython-37m-x86_64-linux-gnu.so
mercury_oxide-0.1.0.dist-info/RECORD
